mixologist/__init__.py
mixologist-0.1.0.dist-info/WHEEL
mixologist-0.1.0.dist-info/METADATA
mixologist-0.1.0.dist-info/RECORD
